nanoCAT/__init__.py
nanoCAT/__version__.py
nanoCAT/cdft.py
nanoCAT/cone_angle.py
nanoCAT/ligand_solvation.py
nanoCAT/mol_bulk.py
nanoCAT/py.typed
nanoCAT/qd_opt_ff.py
nanoCAT/asa/__init__.py
nanoCAT/asa/asa.py
nanoCAT/asa/asa_frag.py
nanoCAT/asa/energy_gatherer.py
nanoCAT/asa/md_asa.py
nanoCAT/bde/__init__.py
nanoCAT/bde/bde_workflow.py
nanoCAT/bde/construct_xyn.py
nanoCAT/bde/dissociate_xyn.py
nanoCAT/bde/guess_core_dist.py
nanoCAT/bde/identify_surface.py
nanoCAT/bulk/__init__.py
nanoCAT/bulk/mol_graph.py
nanoCAT/bulk/mol_graph2.py
nanoCAT/ff/__init__.py
nanoCAT/ff/cp2k_utils.py
nanoCAT/ff/ff_anionic.py
nanoCAT/ff/ff_assignment.py
nanoCAT/ff/ff_cationic.py
nanoCAT/ff/match_job.py
nanoCAT/recipes/__init__.py
nanoCAT/recipes/bulk.py
nanoCAT/recipes/cdft_utils.py
nanoCAT/recipes/charges.py
nanoCAT/recipes/coordination_number.py
nanoCAT/recipes/dissociation.py
nanoCAT/recipes/entropy.py
nanoCAT/recipes/fast_sigma.py
nanoCAT/recipes/mark_surface.py
nanoCAT/recipes/mol_filter.py
nanoCAT/recipes/multi_lig_job.py
Nano_CAT-0.7.2.dist-info/LICENSE.md
Nano_CAT-0.7.2.dist-info/METADATA
Nano_CAT-0.7.2.dist-info/WHEEL
Nano_CAT-0.7.2.dist-info/top_level.txt
Nano_CAT-0.7.2.dist-info/RECORD
