Metadata-Version: 2.1
Name: Nano-CAT
Version: 0.7.2
Summary: A collection of tools for the analysis of nanocrystals.
Home-page: https://github.com/nlesc-nano/nano-CAT
Author: ['Bas van Beek']
Author-email: b.f.van.beek@vu.nl
License: GNU Lesser General Public License v3 or later
Keywords: quantum-mechanics,molecular-mechanics,science,chemistry,python-3,python-3-7,python-3-8,python-3-9,python-3-10,automation,scientific-workflows
Classifier: Development Status :: 4 - Beta
Classifier: Intended Audience :: Science/Research
Classifier: Topic :: Scientific/Engineering :: Chemistry
Classifier: License :: OSI Approved :: GNU General Public License v3 or later (GPLv3+)
Classifier: Natural Language :: English
Classifier: Programming Language :: Python :: 3.7
Classifier: Programming Language :: Python :: 3.8
Classifier: Programming Language :: Python :: 3.9
Classifier: Programming Language :: Python :: 3.10
Classifier: Typing :: Typed
Requires-Python: >=3.7
License-File: LICENSE.md
Requires-Dist: Nano-Utils (>=2.3.1)
Requires-Dist: numpy (>=1.15.0)
Requires-Dist: scipy (>=0.19.1)
Requires-Dist: pandas (>=0.24.0)
Requires-Dist: AssertionLib (>=2.3)
Requires-Dist: noodles (>=0.3.3)
Requires-Dist: more-itertools (>=1.0)
Requires-Dist: plams (>=1.5.1)
Requires-Dist: qmflows (>=0.11.1)
Requires-Dist: nlesc-CAT (>=0.11.1)
Requires-Dist: Auto-FOX (>=0.10.0)
Requires-Dist: rdkit-pypi (>=2018.03.1)
Provides-Extra: test
Requires-Dist: pyyaml (>=5.1) ; extra == 'test'
Requires-Dist: pytest ; extra == 'test'
Requires-Dist: pytest-cov ; extra == 'test'
Requires-Dist: pytest-mock ; extra == 'test'
